flask_environments.py
setup.py
Flask_Environments.egg-info/PKG-INFO
Flask_Environments.egg-info/SOURCES.txt
Flask_Environments.egg-info/dependency_links.txt
Flask_Environments.egg-info/not-zip-safe
Flask_Environments.egg-info/requires.txt
Flask_Environments.egg-info/top_level.txt